inmydata/CalendarAssistant.py
inmydata/ConversationalData.py
inmydata/StructuredData.py
inmydata/__init__.py
inmydata-0.0.18.dist-info/METADATA
inmydata-0.0.18.dist-info/WHEEL
inmydata-0.0.18.dist-info/licenses/LICENSE
inmydata-0.0.18.dist-info/RECORD
