Metadata-Version: 2.4
Name: inmydata
Version: 0.0.18
Summary: This package provides simple API access to the inmydata platform
Project-URL: Homepage, https://inmydata.ai
Project-URL: Documentation, https://developer.inmydata.com
Project-URL: Reference, https://docs.inmydata.ai/agents/
Project-URL: Issues, https://support.inmydata.com
Project-URL: Source, https://github.com/inmydata/agents
Project-URL: Examples, https://github.com/inmydata/agent-examples
Author-email: inmydata <info@inmydata.com>
License-Expression: MIT
License-File: LICENSE
Classifier: Operating System :: OS Independent
Classifier: Programming Language :: Python :: 3
Requires-Python: >=3.9
Requires-Dist: aiohttp>=3.11.18
Requires-Dist: jsonpickle>=4.0.5
Requires-Dist: pandas>=2.3.0
Requires-Dist: requests>=2.32.4
Requires-Dist: signalrcore>=0.9.5
